<?xml version="1.0" encoding="UTF-8"?>

<CmPresetBank>
  <Order>
    <Preset name="Final Breath" crossfade="1.0"/>
    <Preset name="Redemption" crossfade="1.0"/>
    <Preset name="The End of Deception" crossfade="1.0"/>
    <Preset name="Death will Prevail" crossfade="1.0"/>
    <Preset name="My Own Revelation" crossfade="1.0"/>
    <Preset name="Imperious" crossfade="1.0"/>
    <Preset name="Bury the Past" crossfade="1.0"/>
    <Preset name="Dimension Break" crossfade="1.0"/>
    <Preset name="Memento" crossfade="1.0"/>
    <Preset name="Intro" crossfade="1.0"/>
  </Order>
  <Tempo val="120.0"/>
  <BankOrder val="57"/>
</CmPresetBank>
